aerial/__init__.py
aerial/__main__.py
aerial/_version.py
aerial/demo.py
aerial/feed.py
aerial/signalData.py
aerial/wrappers.py
aerial-0.1.0.dist-info/METADATA
aerial-0.1.0.dist-info/RECORD
aerial-0.1.0.dist-info/WHEEL
aerial-0.1.0.dist-info/top_level.txt
