Metadata-Version: 2.1
Name: aerial
Version: 0.1.0
Summary: The easy way to catch signals
Home-page: https://github.com/chrisbrake/aerial
Author: Chris Brake
Author-email: chris.brake@gmail.com
License: UNKNOWN
Keywords: aerial,signals,signal,unix,sighup,sigterm
Platform: UNKNOWN
Classifier: License :: OSI Approved :: BSD License
Classifier: Programming Language :: Python
Classifier: Topic :: Software Development :: Libraries
